[{"pk": 1, "model": "almacenes.marca", "fields": {"descripcion": "Conoco", "abreviatura": "Co"}}, {"pk": 2, "model": "almacenes.marca", "fields": {"descripcion": "Goodyear", "abreviatura": "GY"}}, {"pk": 3, "model": "almacenes.marca", "fields": {"descripcion": "Llantitas", "abreviatura": "LLa"}}, {"pk": 1, "model": "almacenes.unidad", "fields": {"descripcion": "Unidad", "abreviatura": "Und"}}, {"pk": 2, "model": "almacenes.unidad", "fields": {"descripcion": "Litros", "abreviatura": "Lt"}}, {"pk": 3, "model": "almacenes.unidad", "fields": {"descripcion": "Kilogramos", "abreviatura": "Kg"}}, {"pk": 1, "model": "almacenes.producto", "fields": {"pr": "12", "unidad": 1, "abreviatura": "Ar001", "uso": "1", "descripcion": "Aros plateados", "codigo": "0001", "medida": "14", "aro": "13"}}, {"pk": 2, "model": "almacenes.producto", "fields": {"pr": "12", "unidad": 1, "abreviatura": "Fr", "uso": "12", "descripcion": "Frenos", "codigo": "0002", "medida": "12", "aro": "12"}}, {"pk": 1, "model": "almacenes.precioproducto", "fields": {"descripcion": "Precio compra", "producto": 1, "tipo_precio": "C", "precio": 315.0}}, {"pk": 2, "model": "almacenes.precioproducto", "fields": {"descripcion": "Precio aros venta", "producto": 1, "tipo_precio": "V", "precio": 450.75}}, {"pk": 1, "model": "almacenes.sucursal", "fields": {"descripcion": "La Marina", "telefono": "252413", "direccion": "Av. La Marina 356"}}, {"pk": 2, "model": "almacenes.sucursal", "fields": {"descripcion": "Los Incas", "telefono": "354023", "direccion": "Av. Los Incas"}}, {"pk": 1, "model": "almacenes.almacen", "fields": {"descripcion": "Almacen A", "sucursal": 1}}, {"pk": 2, "model": "almacenes.almacen", "fields": {"descripcion": "Almacen B", "sucursal": 2}}, {"pk": 3, "model": "almacenes.almacen", "fields": {"descripcion": "Almacen C", "sucursal": 1}}, {"pk": 1, "model": "almacenes.productoalmacen", "fields": {"producto": 1, "unidades": 200.0, "fecha_vencimiento": "2014-06-03", "almacen": 1, "fecha_ultimo_movimiento": "2013-06-03"}}, {"pk": 2, "model": "almacenes.productoalmacen", "fields": {"producto": 2, "unidades": 100.0, "fecha_vencimiento": "2013-06-03", "almacen": 2, "fecha_ultimo_movimiento": "2013-06-03"}}]